{
 "result": [
  {
   "actorName": "Jonathan René",
   "movieName": "Catch Me If You Can"
  },
  {
   "actorName": "Wendy Worthington",
   "movieName": "Catch Me If You Can"
  },
  {
   "actorName": "Lyne Odums",
   "movieName": "The Ladykillers"
  },
  {
   "actorName": "Daniela Schulz",
   "movieName": "Bridge of Spies"
  },
  {
   "actorName": "Xander Berkeley",
   "movieName": "Apollo 13"
  },
  {
   "actorName": "Billy Crystal",
   "movieName": "Cars"
  },
  {
   "actorName": "John Randolph",
   "movieName": "You've Got Mail"
  },
  {
   "actorName": "Raphaël Cardin",
   "movieName": "Catch Me If You Can"
  },
  {
   "actorName": "Jim Roche",
   "movieName": "Philadelphia"
  },
  {
   "actorName": "B. J. Novak",
   "movieName": "Saving Mr. Banks"
  },
  {
   "actorName": "Julene Renee",
   "movieName": "The Polar Express"
  },
  {
   "actorName": "Yeardley Smith",
   "movieName": "The Simpsons Movie"
  },
  {
   "actorName": "Leo Stransky",
   "movieName": "Saving Private Ryan"
  },
  {
   "actorName": "Jon Donahue",
   "movieName": "Bridge of Spies"
  },
  {
   "actorName": "Colin Farrell",
   "movieName": "Saving Mr. Banks"
  },
  {
   "actorName": "Hugo Weaving",
   "movieName": "Cloud Atlas"
  },
  {
   "actorName": "Wes McGee",
   "movieName": "Bridge of Spies"
  },
  {
   "actorName": "Maggie Mellin",
   "movieName": "Catch Me If You Can"
  },
  {
   "actorName": "Dawn Maxey",
   "movieName": "That Thing You Do!"
  },
  {
   "actorName": "Brett Cullen",
   "movieName": "Apollo 13"
  },
  {
   "actorName": "David Ross Paterson",
   "movieName": "Saving Mr. Banks"
  },
  {
   "actorName": "Sarah Freeman",
   "movieName": "Toy Story"
  },
  {
   "actorName": "Ian Porter",
   "movieName": "Saving Private Ryan"
  },
  {
   "actorName": "E.J. Holowicki",
   "movieName": "Cars"
  },
  {
   "actorName": "David Warshofsky",
   "movieName": "Captain Phillips"
  },
  {
   "actorName": "Michael Gaston",
   "movieName": "Bridge of Spies"
  },
  {
   "actorName": "Jake Wagner",
   "movieName": "Catch Me If You Can"
  },
  {
   "actorName": "Amr El-Bayoumi",
   "movieName": "Captain Phillips"
  },
  {
   "actorName": "Jon Curry",
   "movieName": "Bridge of Spies"
  },
  {
   "actorName": "Michael Kemmerling",
   "movieName": "Forrest Gump"
  },
  {
   "actorName": "Robin Wright",
   "movieName": "Forrest Gump"
  },
  {
   "actorName": "Gary Howard Klar",
   "movieName": "Big"
  },
  {
   "actorName": "Sarah Clark",
   "movieName": "Cars"
  },
  {
   "actorName": "Wynn Everett",
   "movieName": "Charlie Wilson's War"
  },
  {
   "actorName": "Brent Briscoe",
   "movieName": "The Green Mile"
  },
  {
   "actorName": "Beatrice Miller",
   "movieName": "Toy Story 3"
  },
  {
   "actorName": "Alfred Molina",
   "movieName": "The Da Vinci Code"
  },
  {
   "actorName": "Emily Blunt",
   "movieName": "Charlie Wilson's War"
  },
  {
   "actorName": "Nick Searcy",
   "movieName": "Cast Away"
  },
  {
   "actorName": "Jeffrey Williamson",
   "movieName": "Philadelphia"
  },
  {
   "actorName": "Jaime Ray Newman",
   "movieName": "Catch Me If You Can"
  },
  {
   "actorName": "Tony Devon",
   "movieName": "Philadelphia"
  },
  {
   "actorName": "Ciarán Hinds",
   "movieName": "Road to Perdition"
  },
  {
   "actorName": "Rebecca Klingler",
   "movieName": "The Green Mile"
  },
  {
   "actorName": "Tyler Hoechlin",
   "movieName": "Road to Perdition"
  },
  {
   "actorName": "Mark Roper",
   "movieName": "The Da Vinci Code"
  },
  {
   "actorName": "Steve Griffin",
   "movieName": "Saving Private Ryan"
  },
  {
   "actorName": "Jim Antonio",
   "movieName": "Catch Me If You Can"
  },
  {
   "actorName": "Jonathan Dankner",
   "movieName": "Catch Me If You Can"
  },
  {
   "actorName": "Bob Yerkes",
   "movieName": "Angels \u0026 Demons"
  },
  {
   "actorName": "Téa Leoni",
   "movieName": "A League of Their Own"
  },
  {
   "actorName": "Yul Vazquez",
   "movieName": "Captain Phillips"
  },
  {
   "actorName": "Grace Gummer",
   "movieName": "Larry Crowne"
  },
  {
   "actorName": "Sonny Shroyer",
   "movieName": "Forrest Gump"
  },
  {
   "actorName": "Tiffany Salerno",
   "movieName": "Forrest Gump"
  },
  {
   "actorName": "Charles Fleischer",
   "movieName": "The Polar Express"
  },
  {
   "actorName": "Sarah Koskoff",
   "movieName": "That Thing You Do!"
  },
  {
   "actorName": "Curt Lowens",
   "movieName": "Angels \u0026 Demons"
  },
  {
   "actorName": "Lorraine Bracco",
   "movieName": "Radio Flyer"
  },
  {
   "actorName": "John Ohkuma",
   "movieName": "Bridge of Spies"
  },
  {
   "actorName": "Melanie Paxson",
   "movieName": "Saving Mr. Banks"
  },
  {
   "actorName": "Brooke Bloom",
   "movieName": "Extremely Loud \u0026 Incredibly Close"
  },
  {
   "actorName": "Nicolas Radeschi",
   "movieName": "Catch Me If You Can"
  },
  {
   "actorName": "Barry Shabaka Henley",
   "movieName": "The Terminal"
  },
  {
   "actorName": "Paul Klementowicz",
   "movieName": "Extremely Loud \u0026 Incredibly Close"
  },
  {
   "actorName": "Timothy McNeil",
   "movieName": "Forrest Gump"
  },
  {
   "actorName": "Angela Sorensen",
   "movieName": "Catch Me If You Can"
  },
  {
   "actorName": "Shelby Zemanek",
   "movieName": "Angels \u0026 Demons"
  },
  {
   "actorName": "Halle Berry",
   "movieName": "Cloud Atlas"
  },
  {
   "actorName": "Lynda Petty",
   "movieName": "Cars"
  },
  {
   "actorName": "Guy Thauvette",
   "movieName": "Catch Me If You Can"
  },
  {
   "actorName": "Ann Cusack",
   "movieName": "A League of Their Own"
  },
  {
   "actorName": "Emily Hahn",
   "movieName": "Toy Story 3"
  },
  {
   "actorName": "Diane Delano",
   "movieName": "The Ladykillers"
  },
  {
   "actorName": "Julia Roberts",
   "movieName": "Charlie Wilson's War"
  },
  {
   "actorName": "Julia Roberts",
   "movieName": "Larry Crowne"
  },
  {
   "actorName": "Jeffrey DeMunn",
   "movieName": "The Green Mile"
  },
  {
   "actorName": "Angus MacInnes",
   "movieName": "Captain Phillips"
  },
  {
   "actorName": "Haley Rawson",
   "movieName": "Bridge of Spies"
  },
  {
   "actorName": "Brian Goodman",
   "movieName": "Catch Me If You Can"
  },
  {
   "actorName": "Jimmie F. Skaggs",
   "movieName": "Catch Me If You Can"
  },
  {
   "actorName": "George Wallace",
   "movieName": "The Ladykillers"
  },
  {
   "actorName": "Julie Kavner",
   "movieName": "The Simpsons Movie"
  },
  {
   "actorName": "Jeremy Piven",
   "movieName": "Cars"
  },
  {
   "actorName": "Joey Perillo",
   "movieName": "Philadelphia"
  },
  {
   "actorName": "Dennis Farina",
   "movieName": "Saving Private Ryan"
  },
  {
   "actorName": "Stephen Dunham",
   "movieName": "Catch Me If You Can"
  },
  {
   "actorName": "Greg Nutcher",
   "movieName": "Bridge of Spies"
  },
  {
   "actorName": "Claudia Stedelin",
   "movieName": "That Thing You Do!"
  },
  {
   "actorName": "Andrew Havill",
   "movieName": "Cloud Atlas"
  },
  {
   "actorName": "Matt Damon",
   "movieName": "Saving Private Ryan"
  },
  {
   "actorName": "Janet Jones",
   "movieName": "A League of Their Own"
  },
  {
   "actorName": "Maggie Roswell",
   "movieName": "The Simpsons Movie"
  },
  {
   "actorName": "Roy Blount, Jr.",
   "movieName": "Philadelphia"
  },
  {
   "actorName": "Dhaffer L'Abidine",
   "movieName": "The Da Vinci Code"
  },
  {
   "actorName": "Andrew Meeks",
   "movieName": "Catch Me If You Can"
  },
  {
   "actorName": "Max Kerstein",
   "movieName": "Catch Me If You Can"
  },
  {
   "actorName": "Dick Cavett",
   "movieName": "Forrest Gump"
  },
  {
   "actorName": "Anna Maguire",
   "movieName": "Saving Private Ryan"
  },
  {
   "actorName": "Haley Joel Osment",
   "movieName": "Forrest Gump"
  },
  {
   "actorName": "Jason Schwartzman",
   "movieName": "Saving Mr. Banks"
  },
  {
   "actorName": "Diane Dorsey",
   "movieName": "Road to Perdition"
  },
  {
   "actorName": "Sebastian Koch",
   "movieName": "Bridge of Spies"
  },
  {
   "actorName": "Laura Waddell",
   "movieName": "Saving Mr. Banks"
  },
  {
   "actorName": "Merab Ninidze",
   "movieName": "Bridge of Spies"
  },
  {
   "actorName": "Mark Ballou",
   "movieName": "Big"
  },
  {
   "actorName": "Robert Curtis Brown",
   "movieName": "Catch Me If You Can"
  },
  {
   "actorName": "Norbert Weisser",
   "movieName": "Angels \u0026 Demons"
  },
  {
   "actorName": "Pascal Petardi",
   "movieName": "Angels \u0026 Demons"
  },
  {
   "actorName": "Wilmer Valderrama",
   "movieName": "Larry Crowne"
  },
  {
   "actorName": "Tre Cool",
   "movieName": "The Simpsons Movie"
  },
  {
   "actorName": "Katherine Helmond",
   "movieName": "Cars"
  },
  {
   "actorName": "Harry Shearer",
   "movieName": "The Simpsons Movie"
  },
  {
   "actorName": "Paul Newman",
   "movieName": "Road to Perdition"
  },
  {
   "actorName": "Paul Newman",
   "movieName": "Cars"
  },
  {
   "actorName": "Lucas Platt",
   "movieName": "Philadelphia"
  },
  {
   "actorName": "Chris Coppola",
   "movieName": "The Polar Express"
  },
  {
   "actorName": "Ford Wheeler",
   "movieName": "Philadelphia"
  },
  {
   "actorName": "Sarah Lancaster",
   "movieName": "Catch Me If You Can"
  },
  {
   "actorName": "Jenifer Lewis",
   "movieName": "Cars"
  },
  {
   "actorName": "Phil Proctor",
   "movieName": "Toy Story 2"
  },
  {
   "actorName": "Hanna Hall",
   "movieName": "Forrest Gump"
  },
  {
   "actorName": "Candice Azzara",
   "movieName": "Catch Me If You Can"
  },
  {
   "actorName": "Adrian Ochoa",
   "movieName": "Cars"
  },
  {
   "actorName": "Kitty K. Green",
   "movieName": "Forrest Gump"
  },
  {
   "actorName": "Joe Ranft",
   "movieName": "Toy Story 2"
  },
  {
   "actorName": "Joe Ranft",
   "movieName": "Cars"
  },
  {
   "actorName": "James DuMont",
   "movieName": "Catch Me If You Can"
  },
  {
   "actorName": "Cedric the Entertainer",
   "movieName": "Larry Crowne"
  },
  {
   "actorName": "Paul Sanchez",
   "movieName": "Cast Away"
  },
  {
   "actorName": "Bud Luckey",
   "movieName": "Toy Story 3"
  },
  {
   "actorName": "Andrew Stanton",
   "movieName": "Toy Story 2"
  },
  {
   "actorName": "Andrew Stanton",
   "movieName": "Cars"
  },
  {
   "actorName": "Audrey Tautou",
   "movieName": "The Da Vinci Code"
  },
  {
   "actorName": "Bryan Cranston",
   "movieName": "Saving Private Ryan"
  },
  {
   "actorName": "Bryan Cranston",
   "movieName": "Larry Crowne"
  },
  {
   "actorName": "Bryan Cranston",
   "movieName": "That Thing You Do!"
  },
  {
   "actorName": "Lari White",
   "movieName": "Cast Away"
  },
  {
   "actorName": "Pam Grier",
   "movieName": "Larry Crowne"
  },
  {
   "actorName": "Patricia Clarkson",
   "movieName": "The Green Mile"
  },
  {
   "actorName": "Harry Groener",
   "movieName": "Road to Perdition"
  },
  {
   "actorName": "Steve Witting",
   "movieName": "Catch Me If You Can"
  },
  {
   "actorName": "Simon Houle-Gauthier",
   "movieName": "Catch Me If You Can"
  },
  {
   "actorName": "Richard D'Alessandro",
   "movieName": "Forrest Gump"
  },
  {
   "actorName": "John Slattery",
   "movieName": "Charlie Wilson's War"
  },
  {
   "actorName": "Daniel C. Striepeke",
   "movieName": "Forrest Gump"
  },
  {
   "actorName": "Ray Magliozzi",
   "movieName": "Cars"
  },
  {
   "actorName": "Guy-Daniel Tremblay",
   "movieName": "Catch Me If You Can"
  },
  {
   "actorName": "Larry the Cable Guy",
   "movieName": "Cars"
  },
  {
   "actorName": "Max von Sydow",
   "movieName": "Extremely Loud \u0026 Incredibly Close"
  },
  {
   "actorName": "William Marsh",
   "movieName": "Saving Private Ryan"
  },
  {
   "actorName": "Lance Baker",
   "movieName": "Road to Perdition"
  },
  {
   "actorName": "Endre Hules",
   "movieName": "Angels \u0026 Demons"
  },
  {
   "actorName": "Endre Hules",
   "movieName": "Apollo 13"
  },
  {
   "actorName": "Chris Noth",
   "movieName": "Cast Away"
  },
  {
   "actorName": "Faysal  Ahmed",
   "movieName": "Captain Phillips"
  },
  {
   "actorName": "Jeremy Clarkson",
   "movieName": "Cars"
  },
  {
   "actorName": "Kathryn Witt",
   "movieName": "Philadelphia"
  },
  {
   "actorName": "Stephen Mendel",
   "movieName": "The Terminal"
  },
  {
   "actorName": "Sara Ramirez",
   "movieName": "You've Got Mail"
  },
  {
   "actorName": "Giovanni Ribisi",
   "movieName": "Saving Private Ryan"
  },
  {
   "actorName": "Giovanni Ribisi",
   "movieName": "That Thing You Do!"
  },
  {
   "actorName": "David Drake",
   "movieName": "Philadelphia"
  },
  {
   "actorName": "José Castillo",
   "movieName": "Philadelphia"
  },
  {
   "actorName": "Phil Hawn",
   "movieName": "The Green Mile"
  },
  {
   "actorName": "Madonna",
   "movieName": "A League of Their Own"
  },
  {
   "actorName": "Susan Sarandon",
   "movieName": "Cloud Atlas"
  },
  {
   "actorName": "Stephen Henderson",
   "movieName": "Extremely Loud \u0026 Incredibly Close"
  },
  {
   "actorName": "Joshua Harto",
   "movieName": "Bridge of Spies"
  },
  {
   "actorName": "Dennis Hearn",
   "movieName": "Extremely Loud \u0026 Incredibly Close"
  },
  {
   "actorName": "Kelsey Grammer",
   "movieName": "Toy Story 2"
  },
  {
   "actorName": "Kelsey Grammer",
   "movieName": "The Simpsons Movie"
  },
  {
   "actorName": "Paula Malcomson",
   "movieName": "The Green Mile"
  },
  {
   "actorName": "J.K. Simmons",
   "movieName": "The Ladykillers"
  },
  {
   "actorName": "Zoe Saldana",
   "movieName": "The Terminal"
  },
  {
   "actorName": "Sam Anderson",
   "movieName": "Forrest Gump"
  },
  {
   "actorName": "Sébastien Jean",
   "movieName": "Catch Me If You Can"
  },
  {
   "actorName": "Jennifer Kan",
   "movieName": "Catch Me If You Can"
  },
  {
   "actorName": "Robb Skyler",
   "movieName": "Forrest Gump"
  },
  {
   "actorName": "Rachel Griffiths",
   "movieName": "Saving Mr. Banks"
  },
  {
   "actorName": "Clint Howard",
   "movieName": "Apollo 13"
  },
  {
   "actorName": "Seamus McQuade",
   "movieName": "Saving Private Ryan"
  },
  {
   "actorName": "Danny Mann",
   "movieName": "Toy Story 3"
  },
  {
   "actorName": "David Gyasi",
   "movieName": "Cloud Atlas"
  },
  {
   "actorName": "John William Galt",
   "movieName": "Forrest Gump"
  },
  {
   "actorName": "Jim C. Ferris",
   "movieName": "Bridge of Spies"
  },
  {
   "actorName": "Patrice Dussault ",
   "movieName": "Catch Me If You Can"
  },
  {
   "actorName": "Eve Brent",
   "movieName": "The Green Mile"
  },
  {
   "actorName": "Colleen O'Shaughnessey",
   "movieName": "Toy Story 3"
  },
  {
   "actorName": "Shane Edelman",
   "movieName": "Catch Me If You Can"
  },
  {
   "actorName": "Max Martini",
   "movieName": "Saving Private Ryan"
  },
  {
   "actorName": "Max Martini",
   "movieName": "Captain Phillips"
  },
  {
   "actorName": "Christopher Walken",
   "movieName": "Catch Me If You Can"
  },
  {
   "actorName": "Silvano Marchetto",
   "movieName": "Angels \u0026 Demons"
  },
  {
   "actorName": "Adam Hendershott",
   "movieName": "Radio Flyer"
  },
  {
   "actorName": "Thom Barry",
   "movieName": "Apollo 13"
  },
  {
   "actorName": "Mark Fichera",
   "movieName": "Bridge of Spies"
  },
  {
   "actorName": "Michael Chernus",
   "movieName": "Captain Phillips"
  },
  {
   "actorName": "Anna Deavere Smith",
   "movieName": "Philadelphia"
  },
  {
   "actorName": "Q. Lazzarus",
   "movieName": "Philadelphia"
  },
  {
   "actorName": "Julius Erving",
   "movieName": "Philadelphia"
  },
  {
   "actorName": "Warren Miller",
   "movieName": "Philadelphia"
  },
  {
   "actorName": "Estelle Harris",
   "movieName": "Toy Story 3"
  },
  {
   "actorName": "Estelle Harris",
   "movieName": "Toy Story 2"
  },
  {
   "actorName": "Laurie Metcalf",
   "movieName": "Toy Story 3"
  },
  {
   "actorName": "Laurie Metcalf",
   "movieName": "Toy Story 2"
  },
  {
   "actorName": "Laurie Metcalf",
   "movieName": "Toy Story"
  },
  {
   "actorName": "Jessica Collins",
   "movieName": "Catch Me If You Can"
  },
  {
   "actorName": "San Shella",
   "movieName": "Captain Phillips"
  },
  {
   "actorName": "Yan Cui",
   "movieName": "Angels \u0026 Demons"
  },
  {
   "actorName": "Amy Ryan",
   "movieName": "Bridge of Spies"
  },
  {
   "actorName": "Geoffrey Blake",
   "movieName": "Forrest Gump"
  },
  {
   "actorName": "Jay Leno",
   "movieName": "Cars"
  },
  {
   "actorName": "Heidi Jayne Netzley",
   "movieName": "Road to Perdition"
  },
  {
   "actorName": "Tim Allen",
   "movieName": "Toy Story 3"
  },
  {
   "actorName": "Tim Allen",
   "movieName": "Toy Story 2"
  },
  {
   "actorName": "Tim Allen",
   "movieName": "Cars"
  },
  {
   "actorName": "Tim Allen",
   "movieName": "Toy Story"
  },
  {
   "actorName": "Harry Northup",
   "movieName": "Philadelphia"
  },
  {
   "actorName": "Jeff Garlin",
   "movieName": "Toy Story 3"
  },
  {
   "actorName": "Nona Gaye",
   "movieName": "The Polar Express"
  },
  {
   "actorName": "Shecky Greene",
   "movieName": "Splash"
  },
  {
   "actorName": "Masasa Moyo",
   "movieName": "Angels \u0026 Demons"
  },
  {
   "actorName": "Rainer Reiners",
   "movieName": "Bridge of Spies"
  },
  {
   "actorName": "Chris Mulkey",
   "movieName": "Captain Phillips"
  },
  {
   "actorName": "Mike Jolly",
   "movieName": "Forrest Gump"
  },
  {
   "actorName": "Richard Rosetti",
   "movieName": "Angels \u0026 Demons"
  },
  {
   "actorName": "Tracey Walter",
   "movieName": "Philadelphia"
  },
  {
   "actorName": "Will Rogers",
   "movieName": "Bridge of Spies"
  },
  {
   "actorName": "Miko Hughes",
   "movieName": "Apollo 13"
  },
  {
   "actorName": "Thomas Kopache",
   "movieName": "Catch Me If You Can"
  },
  {
   "actorName": "Chi McBride",
   "movieName": "The Terminal"
  },
  {
   "actorName": "Peter Pedrero",
   "movieName": "The Da Vinci Code"
  },
  {
   "actorName": "Jenson Smith",
   "movieName": "Extremely Loud \u0026 Incredibly Close"
  },
  {
   "actorName": "Peggy Roeder",
   "movieName": "Road to Perdition"
  },
  {
   "actorName": "Jacqueline Lovell",
   "movieName": "Forrest Gump"
  },
  {
   "actorName": "Roxana Ortega",
   "movieName": "Larry Crowne"
  },
  {
   "actorName": "Burghart Klaußner",
   "movieName": "Bridge of Spies"
  },
  {
   "actorName": "Demetri Goritsas",
   "movieName": "Saving Private Ryan"
  },
  {
   "actorName": "Howard Mungo",
   "movieName": "Angels \u0026 Demons"
  },
  {
   "actorName": "Lilyan Chauvin",
   "movieName": "Catch Me If You Can"
  },
  {
   "actorName": "Eve Hewson",
   "movieName": "Bridge of Spies"
  },
  {
   "actorName": "Max Elliott Slade",
   "movieName": "Apollo 13"
  },
  {
   "actorName": "Mike Nelson",
   "movieName": "Cars"
  },
  {
   "actorName": "Jack Knight",
   "movieName": "Catch Me If You Can"
  },
  {
   "actorName": "Dabbs Greer",
   "movieName": "The Green Mile"
  },
  {
   "actorName": "Peter Conboy",
   "movieName": "Bridge of Spies"
  },
  {
   "actorName": "Ellis Hall",
   "movieName": "Catch Me If You Can"
  },
  {
   "actorName": "Holmes Osborne",
   "movieName": "That Thing You Do!"
  },
  {
   "actorName": "Lawrence T. Wrentz",
   "movieName": "Philadelphia"
  },
  {
   "actorName": "Lauren Cohn",
   "movieName": "Catch Me If You Can"
  },
  {
   "actorName": "Abraham Verduzco",
   "movieName": "Radio Flyer"
  },
  {
   "actorName": "Greg Grunberg",
   "movieName": "The Ladykillers"
  },
  {
   "actorName": "Daniel von Bargen",
   "movieName": "Philadelphia"
  },
  {
   "actorName": "Josh Clark",
   "movieName": "Big"
  },
  {
   "actorName": "Azeez Mohammed",
   "movieName": "Captain Phillips"
  },
  {
   "actorName": "Tracy Howe",
   "movieName": "Bridge of Spies"
  },
  {
   "actorName": "Paul Bettany",
   "movieName": "The Da Vinci Code"
  },
  {
   "actorName": "Ana Leza",
   "movieName": "Philadelphia"
  },
  {
   "actorName": "Joe Mantegna",
   "movieName": "The Simpsons Movie"
  },
  {
   "actorName": "Lily Bigham",
   "movieName": "Saving Mr. Banks"
  },
  {
   "actorName": "Jeff Pidgeon",
   "movieName": "Toy Story 3"
  },
  {
   "actorName": "Jeff Pidgeon",
   "movieName": "Toy Story 2"
  },
  {
   "actorName": "Oliver Block",
   "movieName": "Big"
  },
  {
   "actorName": "Ted Hollis",
   "movieName": "The Green Mile"
  },
  {
   "actorName": "Don Fischer",
   "movieName": "Forrest Gump"
  },
  {
   "actorName": "Ron Vawter",
   "movieName": "Philadelphia"
  },
  {
   "actorName": "Steve Franken",
   "movieName": "Angels \u0026 Demons"
  },
  {
   "actorName": "John Finn",
   "movieName": "Catch Me If You Can"
  },
  {
   "actorName": "Dylan Baker",
   "movieName": "Road to Perdition"
  },
  {
   "actorName": "Steven Meizler",
   "movieName": "Catch Me If You Can"
  },
  {
   "actorName": "Gary Goetzman",
   "movieName": "Philadelphia"
  },
  {
   "actorName": "Christopher Jones",
   "movieName": "Forrest Gump"
  },
  {
   "actorName": "David Allen Brooks",
   "movieName": "Cast Away"
  },
  {
   "actorName": "Russi Taylor",
   "movieName": "The Simpsons Movie"
  },
  {
   "actorName": "Shiri Appleby",
   "movieName": "Charlie Wilson's War"
  },
  {
   "actorName": "Catherine Keener",
   "movieName": "Captain Phillips"
  },
  {
   "actorName": "Stephanie Roth Haberle",
   "movieName": "Philadelphia"
  },
  {
   "actorName": "Morgan Rusler",
   "movieName": "Catch Me If You Can"
  },
  {
   "actorName": "Lazarus Jackson",
   "movieName": "Forrest Gump"
  },
  {
   "actorName": "Blake Clark",
   "movieName": "Toy Story 3"
  },
  {
   "actorName": "Nathan Fillion",
   "movieName": "Saving Private Ryan"
  },
  {
   "actorName": "Jonathan Harris",
   "movieName": "Toy Story 2"
  },
  {
   "actorName": "Cheech Marin",
   "movieName": "Cars"
  },
  {
   "actorName": "Meg Ryan",
   "movieName": "You've Got Mail"
  },
  {
   "actorName": "Bill McKinney",
   "movieName": "The Green Mile"
  },
  {
   "actorName": "Troy Christian",
   "movieName": "Forrest Gump"
  },
  {
   "actorName": "John Magaro",
   "movieName": "Captain Phillips"
  },
  {
   "actorName": "Malachi Weir",
   "movieName": "Extremely Loud \u0026 Incredibly Close"
  },
  {
   "actorName": "Henny Russell",
   "movieName": "Bridge of Spies"
  },
  {
   "actorName": "Jillian Lebling",
   "movieName": "Bridge of Spies"
  },
  {
   "actorName": "Jodi Benson",
   "movieName": "Toy Story 3"
  },
  {
   "actorName": "Jodi Benson",
   "movieName": "Toy Story 2"
  },
  {
   "actorName": "David Morse",
   "movieName": "The Green Mile"
  },
  {
   "actorName": "Kumar Pallana",
   "movieName": "The Terminal"
  },
  {
   "actorName": "Alistair Petrie",
   "movieName": "Cloud Atlas"
  },
  {
   "actorName": "Lori Petty",
   "movieName": "A League of Their Own"
  },
  {
   "actorName": "Julian Tepper",
   "movieName": "Extremely Loud \u0026 Incredibly Close"
  },
  {
   "actorName": "Brett Rice",
   "movieName": "Forrest Gump"
  },
  {
   "actorName": "Ray Proscia",
   "movieName": "Catch Me If You Can"
  },
  {
   "actorName": "Andre B. Blake",
   "movieName": "Philadelphia"
  },
  {
   "actorName": "Elizabeth Banks",
   "movieName": "Catch Me If You Can"
  },
  {
   "actorName": "Alexandre Pepin",
   "movieName": "Catch Me If You Can"
  },
  {
   "actorName": "Dakin Matthews",
   "movieName": "Bridge of Spies"
  },
  {
   "actorName": "Mya-Lecia Naylor",
   "movieName": "Cloud Atlas"
  },
  {
   "actorName": "Mary Kate Schellhardt",
   "movieName": "Apollo 13"
  },
  {
   "actorName": "Joanne Woodward",
   "movieName": "Philadelphia"
  },
  {
   "actorName": "Kevin Pollak",
   "movieName": "That Thing You Do!"
  },
  {
   "actorName": "Frank Welker",
   "movieName": "Toy Story 3"
  },
  {
   "actorName": "Jude Law",
   "movieName": "Road to Perdition"
  },
  {
   "actorName": "Sarah Rush",
   "movieName": "Catch Me If You Can"
  },
  {
   "actorName": "Maureen Gallagher",
   "movieName": "Road to Perdition"
  },
  {
   "actorName": "Rachel Nichols",
   "movieName": "Charlie Wilson's War"
  },
  {
   "actorName": "Christian Clemenson",
   "movieName": "Apollo 13"
  },
  {
   "actorName": "Jared Rushton",
   "movieName": "Big"
  },
  {
   "actorName": "Kristen Schaal",
   "movieName": "Toy Story 3"
  },
  {
   "actorName": "Chandra Wilson",
   "movieName": "Philadelphia"
  },
  {
   "actorName": "Larry Benton",
   "movieName": "Cars"
  },
  {
   "actorName": "Hank Azaria",
   "movieName": "The Simpsons Movie"
  },
  {
   "actorName": "Austin Stowell",
   "movieName": "Bridge of Spies"
  },
  {
   "actorName": "Joe Starr",
   "movieName": "Bridge of Spies"
  },
  {
   "actorName": "Kathleen Byron",
   "movieName": "Saving Private Ryan"
  },
  {
   "actorName": "David Strathairn",
   "movieName": "A League of Their Own"
  },
  {
   "actorName": "Heather Burns",
   "movieName": "You've Got Mail"
  },
  {
   "actorName": "Julian Spencer",
   "movieName": "Saving Private Ryan"
  },
  {
   "actorName": "Andy McPhee",
   "movieName": "Saving Mr. Banks"
  },
  {
   "actorName": "Ian Barford",
   "movieName": "Road to Perdition"
  },
  {
   "actorName": "Bobby Di Cicco",
   "movieName": "Splash"
  },
  {
   "actorName": "Jean-Yves Berteloot",
   "movieName": "The Da Vinci Code"
  },
  {
   "actorName": "Graham Greene",
   "movieName": "The Green Mile"
  },
  {
   "actorName": "Corey Reynolds",
   "movieName": "The Terminal"
  },
  {
   "actorName": "Rafael Gareisen",
   "movieName": "Bridge of Spies"
  },
  {
   "actorName": "Susan Slome",
   "movieName": "The Terminal"
  },
  {
   "actorName": "Catherine Zeta-Jones",
   "movieName": "The Terminal"
  },
  {
   "actorName": "Michele Little",
   "movieName": "Apollo 13"
  },
  {
   "actorName": "Alexander Bisping",
   "movieName": "Catch Me If You Can"
  },
  {
   "actorName": "Nancy Lenehan",
   "movieName": "Catch Me If You Can"
  },
  {
   "actorName": "Joe Alaskey",
   "movieName": "Forrest Gump"
  },
  {
   "actorName": "August Wittgenstein",
   "movieName": "Angels \u0026 Demons"
  },
  {
   "actorName": "Sally Field",
   "movieName": "Forrest Gump"
  },
  {
   "actorName": "Paul Schmitz",
   "movieName": "Angels \u0026 Demons"
  },
  {
   "actorName": "Seth Gabel",
   "movieName": "The Da Vinci Code"
  },
  {
   "actorName": "Jason McNally",
   "movieName": "Catch Me If You Can"
  },
  {
   "actorName": "Paul Jude Letersky",
   "movieName": "Bridge of Spies"
  },
  {
   "actorName": "Jean-François Brousseau",
   "movieName": "Catch Me If You Can"
  },
  {
   "actorName": "James Lorinz",
   "movieName": "Bridge of Spies"
  },
  {
   "actorName": "Jean Reno",
   "movieName": "The Da Vinci Code"
  },
  {
   "actorName": "Amy Acker",
   "movieName": "Catch Me If You Can"
  },
  {
   "actorName": "Marc-Antoine Côté",
   "movieName": "Catch Me If You Can"
  },
  {
   "actorName": "Steven Tyler",
   "movieName": "The Polar Express"
  },
  {
   "actorName": "Tom Magliozzi",
   "movieName": "Cars"
  },
  {
   "actorName": "Maile Flanagan",
   "movieName": "The Simpsons Movie"
  },
  {
   "actorName": "Jack Angel",
   "movieName": "Toy Story 3"
  },
  {
   "actorName": "Gene Borkan",
   "movieName": "Philadelphia"
  },
  {
   "actorName": "Dan Olmstead",
   "movieName": "Philadelphia"
  },
  {
   "actorName": "Benita Krista Nall",
   "movieName": "Catch Me If You Can"
  },
  {
   "actorName": "William Lauzon",
   "movieName": "Catch Me If You Can"
  },
  {
   "actorName": "Alex Rocco",
   "movieName": "That Thing You Do!"
  },
  {
   "actorName": "Ayelet Zurer",
   "movieName": "Angels \u0026 Demons"
  },
  {
   "actorName": "Niall Greig Fulton",
   "movieName": "Cloud Atlas"
  },
  {
   "actorName": "Jesse Plemons",
   "movieName": "Bridge of Spies"
  },
  {
   "actorName": "Jane Edith Wilson",
   "movieName": "Catch Me If You Can"
  },
  {
   "actorName": "John Judd",
   "movieName": "Road to Perdition"
  },
  {
   "actorName": "Charles Techman",
   "movieName": "Philadelphia"
  },
  {
   "actorName": "Andrew Lipschultz",
   "movieName": "Apollo 13"
  },
  {
   "actorName": "Ethan Embry",
   "movieName": "That Thing You Do!"
  },
  {
   "actorName": "John Morris",
   "movieName": "Toy Story 3"
  },
  {
   "actorName": "John Morris",
   "movieName": "Toy Story 2"
  },
  {
   "actorName": "John Morris",
   "movieName": "Toy Story"
  },
  {
   "actorName": "Jean-Pierre Marielle",
   "movieName": "The Da Vinci Code"
  },
  {
   "actorName": "Karl Wiedergott",
   "movieName": "The Simpsons Movie"
  },
  {
   "actorName": "Irma P. Hall",
   "movieName": "The Ladykillers"
  },
  {
   "actorName": "Eddie Santiago",
   "movieName": "The Terminal"
  },
  {
   "actorName": "Annie Potts",
   "movieName": "Toy Story 2"
  },
  {
   "actorName": "Annie Potts",
   "movieName": "Toy Story"
  },
  {
   "actorName": "Tom Detrik",
   "movieName": "Philadelphia"
  },
  {
   "actorName": "R. Lee Ermey",
   "movieName": "Toy Story 3"
  },
  {
   "actorName": "R. Lee Ermey",
   "movieName": "Toy Story 2"
  },
  {
   "actorName": "R. Lee Ermey",
   "movieName": "Toy Story"
  },
  {
   "actorName": "Guillermo Díaz",
   "movieName": "The Terminal"
  },
  {
   "actorName": "Jane Bodle",
   "movieName": "Catch Me If You Can"
  },
  {
   "actorName": "Harry Dean Stanton",
   "movieName": "The Green Mile"
  },
  {
   "actorName": "Bill Cobbs",
   "movieName": "That Thing You Do!"
  },
  {
   "actorName": "Jeremy Howard",
   "movieName": "Catch Me If You Can"
  },
  {
   "actorName": "James Brolin",
   "movieName": "Catch Me If You Can"
  },
  {
   "actorName": "Deborah Kellner",
   "movieName": "Catch Me If You Can"
  },
  {
   "actorName": "J. Patrick McCormack",
   "movieName": "Catch Me If You Can"
  },
  {
   "actorName": "Joerg Stadler",
   "movieName": "Saving Private Ryan"
  },
  {
   "actorName": "Jennifer Manley",
   "movieName": "Catch Me If You Can"
  },
  {
   "actorName": "Babaloo Mandel",
   "movieName": "Splash"
  },
  {
   "actorName": "Robert Loggia",
   "movieName": "Big"
  },
  {
   "actorName": "Brandon Keener",
   "movieName": "Catch Me If You Can"
  },
  {
   "actorName": "Dmitri S. Boudrine",
   "movieName": "Cast Away"
  },
  {
   "actorName": "Thomas Morris",
   "movieName": "Angels \u0026 Demons"
  },
  {
   "actorName": "Michael Wren Gucciardo",
   "movieName": "Bridge of Spies"
  },
  {
   "actorName": "Jeffrey Wright",
   "movieName": "Extremely Loud \u0026 Incredibly Close"
  },
  {
   "actorName": "Dave Chappelle",
   "movieName": "You've Got Mail"
  },
  {
   "actorName": "Brody Nicholas Lee",
   "movieName": "Cloud Atlas"
  },
  {
   "actorName": "Charles Glenn",
   "movieName": "Philadelphia"
  },
  {
   "actorName": "Cara Seymour",
   "movieName": "You've Got Mail"
  },
  {
   "actorName": "Antonio Banderas",
   "movieName": "Philadelphia"
  },
  {
   "actorName": "Bill Pullman",
   "movieName": "A League of Their Own"
  },
  {
   "actorName": "Donna Kimball",
   "movieName": "Catch Me If You Can"
  },
  {
   "actorName": "Jonas Fisch",
   "movieName": "Angels \u0026 Demons"
  },
  {
   "actorName": "John Eddins",
   "movieName": "The Terminal"
  },
  {
   "actorName": "Alex Hyde-White",
   "movieName": "Catch Me If You Can"
  },
  {
   "actorName": "Dabney Coleman",
   "movieName": "You've Got Mail"
  },
  {
   "actorName": "Mykelti Williamson",
   "movieName": "Forrest Gump"
  },
  {
   "actorName": "François Duhamel",
   "movieName": "Cast Away"
  },
  {
   "actorName": "Albert Brooks",
   "movieName": "The Simpsons Movie"
  },
  {
   "actorName": "Edward Burns",
   "movieName": "Saving Private Ryan"
  },
  {
   "actorName": "Victor DiMattia",
   "movieName": "Radio Flyer"
  },
  {
   "actorName": "Stanley Tucci",
   "movieName": "Road to Perdition"
  },
  {
   "actorName": "Stanley Tucci",
   "movieName": "The Terminal"
  },
  {
   "actorName": "Peter Scolari",
   "movieName": "The Polar Express"
  },
  {
   "actorName": "Peter Scolari",
   "movieName": "That Thing You Do!"
  },
  {
   "actorName": "Ryan Hurst",
   "movieName": "The Ladykillers"
  },
  {
   "actorName": "Joel Ewing",
   "movieName": "Catch Me If You Can"
  },
  {
   "actorName": "Ned Beatty",
   "movieName": "Toy Story 3"
  },
  {
   "actorName": "Ned Beatty",
   "movieName": "Charlie Wilson's War"
  },
  {
   "actorName": "Armin Mueller-Stahl",
   "movieName": "Angels \u0026 Demons"
  },
  {
   "actorName": "Anthony Powers",
   "movieName": "Catch Me If You Can"
  },
  {
   "actorName": "Sarah Mahoney",
   "movieName": "Larry Crowne"
  },
  {
   "actorName": "Jean-François Blanchard",
   "movieName": "Catch Me If You Can"
  },
  {
   "actorName": "Jim Ward",
   "movieName": "Toy Story 3"
  },
  {
   "actorName": "Ruth Wilson",
   "movieName": "Saving Mr. Banks"
  },
  {
   "actorName": "Bill Rowe",
   "movieName": "Philadelphia"
  },
  {
   "actorName": "Dominic Bond",
   "movieName": "Catch Me If You Can"
  },
  {
   "actorName": "Martin Docherty",
   "movieName": "Cloud Atlas"
  },
  {
   "actorName": "Malachi Throne",
   "movieName": "Catch Me If You Can"
  },
  {
   "actorName": "David Moscow",
   "movieName": "Big"
  },
  {
   "actorName": "Nadja Bobyleva",
   "movieName": "Bridge of Spies"
  },
  {
   "actorName": "Harrison Young",
   "movieName": "Saving Private Ryan"
  },
  {
   "actorName": "Alfred Dennis",
   "movieName": "Catch Me If You Can"
  },
  {
   "actorName": "Pierfrancesco Favino",
   "movieName": "Angels \u0026 Demons"
  },
  {
   "actorName": "Stephen Kunken",
   "movieName": "Bridge of Spies"
  },
  {
   "actorName": "Gabriel Jarret",
   "movieName": "Apollo 13"
  },
  {
   "actorName": "Peter Jacobs",
   "movieName": "Philadelphia"
  },
  {
   "actorName": "Doug Spinuzza",
   "movieName": "Road to Perdition"
  },
  {
   "actorName": "Jim Lovell",
   "movieName": "Apollo 13"
  },
  {
   "actorName": "Michael Wallis",
   "movieName": "Cars"
  },
  {
   "actorName": "Victor Verhaeghe",
   "movieName": "Bridge of Spies"
  },
  {
   "actorName": "George Kelly",
   "movieName": "Forrest Gump"
  },
  {
   "actorName": "John Goodman",
   "movieName": "Cars"
  },
  {
   "actorName": "John Goodman",
   "movieName": "Extremely Loud \u0026 Incredibly Close"
  },
  {
   "actorName": "William Sadler",
   "movieName": "The Green Mile"
  },
  {
   "actorName": "Kimberlee M. Davis",
   "movieName": "Big"
  },
  {
   "actorName": "Buzz Kilman",
   "movieName": "Philadelphia"
  },
  {
   "actorName": "Joachim Paul Assböck",
   "movieName": "Bridge of Spies"
  },
  {
   "actorName": "Roberta Maxwell",
   "movieName": "Philadelphia"
  },
  {
   "actorName": "Zhou Xun",
   "movieName": "Cloud Atlas"
  },
  {
   "actorName": "Kevin Chamberlin",
   "movieName": "Road to Perdition"
  },
  {
   "actorName": "Lou Romano",
   "movieName": "Cars"
  },
  {
   "actorName": "Richard Kind",
   "movieName": "Toy Story 3"
  },
  {
   "actorName": "Richard Kind",
   "movieName": "Cars"
  },
  {
   "actorName": "Yesenia Adame",
   "movieName": "Angels \u0026 Demons"
  },
  {
   "actorName": "Nolan Lyons",
   "movieName": "Bridge of Spies"
  },
  {
   "actorName": "Matthew Kimbrough",
   "movieName": "Catch Me If You Can"
  },
  {
   "actorName": "Bonnie Hunt",
   "movieName": "Toy Story 3"
  },
  {
   "actorName": "Bonnie Hunt",
   "movieName": "Cars"
  },
  {
   "actorName": "Bonnie Hunt",
   "movieName": "The Green Mile"
  },
  {
   "actorName": "Teresa Ganzel",
   "movieName": "Toy Story 3"
  },
  {
   "actorName": "Bae Doona",
   "movieName": "Cloud Atlas"
  },
  {
   "actorName": "James Cromwell",
   "movieName": "The Green Mile"
  },
  {
   "actorName": "Barry Pepper",
   "movieName": "Saving Private Ryan"
  },
  {
   "actorName": "Barry Pepper",
   "movieName": "The Green Mile"
  },
  {
   "actorName": "Liam Aiken",
   "movieName": "Road to Perdition"
  },
  {
   "actorName": "Charlize Theron",
   "movieName": "That Thing You Do!"
  },
  {
   "actorName": "Charles Boswell",
   "movieName": "Forrest Gump"
  },
  {
   "actorName": "Coleby Lombardo",
   "movieName": "Radio Flyer"
  },
  {
   "actorName": "Dee Croxton",
   "movieName": "The Green Mile"
  },
  {
   "actorName": "James D'Arcy",
   "movieName": "Cloud Atlas"
  },
  {
   "actorName": "Dave Hager",
   "movieName": "Catch Me If You Can"
  },
  {
   "actorName": "Sasha Spielberg",
   "movieName": "The Terminal"
  },
  {
   "actorName": "Frank Abagnale Jr.",
   "movieName": "Catch Me If You Can"
  },
  {
   "actorName": "Paul Lazar",
   "movieName": "Philadelphia"
  },
  {
   "actorName": "Robert Ruth",
   "movieName": "Catch Me If You Can"
  },
  {
   "actorName": "Joe Forbrich",
   "movieName": "Bridge of Spies"
  },
  {
   "actorName": "Hazelle Goodman",
   "movieName": "Extremely Loud \u0026 Incredibly Close"
  },
  {
   "actorName": "Edie McClurg",
   "movieName": "Cars"
  },
  {
   "actorName": "Michael Mattison",
   "movieName": "Forrest Gump"
  },
  {
   "actorName": "Jed Gillin",
   "movieName": "Forrest Gump"
  },
  {
   "actorName": "Sherry Lynn",
   "movieName": "Toy Story 3"
  },
  {
   "actorName": "Charles Napier",
   "movieName": "Philadelphia"
  },
  {
   "actorName": "Marc Fiorini",
   "movieName": "Angels \u0026 Demons"
  },
  {
   "actorName": "Gerald R. Molen",
   "movieName": "Catch Me If You Can"
  },
  {
   "actorName": "Joan Cusack",
   "movieName": "Toy Story 3"
  },
  {
   "actorName": "Joan Cusack",
   "movieName": "Toy Story 2"
  },
  {
   "actorName": "Patti Pelton",
   "movieName": "A League of Their Own"
  },
  {
   "actorName": "Roderick Peeples",
   "movieName": "Road to Perdition"
  },
  {
   "actorName": "Justin Giddings",
   "movieName": "Angels \u0026 Demons"
  },
  {
   "actorName": "Teddy Newton",
   "movieName": "Toy Story 3"
  },
  {
   "actorName": "Lennard Camarillo",
   "movieName": "Radio Flyer"
  },
  {
   "actorName": "Helen Hunt",
   "movieName": "Cast Away"
  },
  {
   "actorName": "Daniel Cerqueira",
   "movieName": "Saving Private Ryan"
  },
  {
   "actorName": "Bob Penny",
   "movieName": "Forrest Gump"
  },
  {
   "actorName": "Emma Thompson",
   "movieName": "Saving Mr. Banks"
  },
  {
   "actorName": "Wayne Knight",
   "movieName": "Toy Story 2"
  },
  {
   "actorName": "Deborah Rush",
   "movieName": "You've Got Mail"
  },
  {
   "actorName": "Quentin Crisp",
   "movieName": "Philadelphia"
  },
  {
   "actorName": "Philip Seymour Hoffman",
   "movieName": "Charlie Wilson's War"
  },
  {
   "actorName": "Jason Robards",
   "movieName": "Philadelphia"
  },
  {
   "actorName": "Greg Kinnear",
   "movieName": "You've Got Mail"
  },
  {
   "actorName": "Marcia Wallace",
   "movieName": "The Simpsons Movie"
  },
  {
   "actorName": "Robert W. Castle",
   "movieName": "Philadelphia"
  },
  {
   "actorName": "Lori Alan",
   "movieName": "Toy Story 3"
  },
  {
   "actorName": "Howard Morris",
   "movieName": "Splash"
  },
  {
   "actorName": "Don Rickles",
   "movieName": "Toy Story 3"
  },
  {
   "actorName": "Don Rickles",
   "movieName": "Toy Story 2"
  },
  {
   "actorName": "Don Rickles",
   "movieName": "Toy Story"
  },
  {
   "actorName": "Robert Ridgely",
   "movieName": "Philadelphia"
  },
  {
   "actorName": "James Greene",
   "movieName": "Road to Perdition"
  },
  {
   "actorName": "Louis Dempsey",
   "movieName": "Cloud Atlas"
  },
  {
   "actorName": "Mario Andretti",
   "movieName": "Cars"
  },
  {
   "actorName": "Eddie Jones",
   "movieName": "The Terminal"
  },
  {
   "actorName": "Eddie Jones",
   "movieName": "A League of Their Own"
  },
  {
   "actorName": "Jonathan Demme",
   "movieName": "That Thing You Do!"
  },
  {
   "actorName": "Kelly Cohen",
   "movieName": "Catch Me If You Can"
  },
  {
   "actorName": "David Wohl",
   "movieName": "Saving Private Ryan"
  },
  {
   "actorName": "Al Harrington",
   "movieName": "Forrest Gump"
  },
  {
   "actorName": "Robert Fyfe",
   "movieName": "Cloud Atlas"
  },
  {
   "actorName": "Afemo Omilami",
   "movieName": "Forrest Gump"
  },
  {
   "actorName": "Martin Wuttke",
   "movieName": "Cloud Atlas"
  },
  {
   "actorName": "Kaitlin Doubleday",
   "movieName": "Catch Me If You Can"
  },
  {
   "actorName": "Jason Weaver",
   "movieName": "The Ladykillers"
  },
  {
   "actorName": "Adrian Martinez",
   "movieName": "Extremely Loud \u0026 Incredibly Close"
  },
  {
   "actorName": "Adam Baldwin",
   "movieName": "Radio Flyer"
  },
  {
   "actorName": "Mathieu Gaudreault",
   "movieName": "Catch Me If You Can"
  },
  {
   "actorName": "Semion Sudarikov",
   "movieName": "Cast Away"
  },
  {
   "actorName": "Kenneth Choi",
   "movieName": "The Terminal"
  },
  {
   "actorName": "Hayley Feinstein",
   "movieName": "Bridge of Spies"
  },
  {
   "actorName": "Jaime Gomez",
   "movieName": "Philadelphia"
  },
  {
   "actorName": "Billie Joe Armstrong",
   "movieName": "The Simpsons Movie"
  },
  {
   "actorName": "Francis Campeau",
   "movieName": "Catch Me If You Can"
  },
  {
   "actorName": "Jon Lovitz",
   "movieName": "A League of Their Own"
  },
  {
   "actorName": "Jon Lovitz",
   "movieName": "Big"
  },
  {
   "actorName": "Lee Unkrich",
   "movieName": "Toy Story 3"
  },
  {
   "actorName": "Lee Unkrich",
   "movieName": "Toy Story 2"
  },
  {
   "actorName": "Elya Baskin",
   "movieName": "Angels \u0026 Demons"
  },
  {
   "actorName": "Karen Finley",
   "movieName": "Philadelphia"
  },
  {
   "actorName": "Roger Corman",
   "movieName": "Apollo 13"
  },
  {
   "actorName": "Roger Corman",
   "movieName": "Philadelphia"
  },
  {
   "actorName": "Paul Feig",
   "movieName": "That Thing You Do!"
  },
  {
   "actorName": "Guido Quaroni",
   "movieName": "Cars"
  },
  {
   "actorName": "Richard Petty",
   "movieName": "Cars"
  },
  {
   "actorName": "Jim Sturgess",
   "movieName": "Cloud Atlas"
  },
  {
   "actorName": "Götz Otto",
   "movieName": "Cloud Atlas"
  },
  {
   "actorName": "Lara Phillips",
   "movieName": "Road to Perdition"
  },
  {
   "actorName": "Zach Hanner",
   "movieName": "Forrest Gump"
  },
  {
   "actorName": "Chris Messina",
   "movieName": "You've Got Mail"
  },
  {
   "actorName": "Mina Badie",
   "movieName": "Road to Perdition"
  },
  {
   "actorName": "Samuel St-Amour",
   "movieName": "Catch Me If You Can"
  },
  {
   "actorName": "Cheryl Howard",
   "movieName": "Angels \u0026 Demons"
  },
  {
   "actorName": "Jill Matson",
   "movieName": "Catch Me If You Can"
  },
  {
   "actorName": "Keith David",
   "movieName": "Cloud Atlas"
  },
  {
   "actorName": "David Parent-Laliberté",
   "movieName": "Catch Me If You Can"
  },
  {
   "actorName": "Erik von Detten",
   "movieName": "Toy Story 3"
  },
  {
   "actorName": "Erik von Detten",
   "movieName": "Toy Story"
  },
  {
   "actorName": "Randall Park",
   "movieName": "Larry Crowne"
  },
  {
   "actorName": "Obba Babatundé",
   "movieName": "Philadelphia"
  },
  {
   "actorName": "Obba Babatundé",
   "movieName": "That Thing You Do!"
  },
  {
   "actorName": "Harve Presnell",
   "movieName": "Saving Private Ryan"
  },
  {
   "actorName": "Kelly McNair",
   "movieName": "Catch Me If You Can"
  },
  {
   "actorName": "Fred Datig",
   "movieName": "Catch Me If You Can"
  },
  {
   "actorName": "Roger Léger",
   "movieName": "Catch Me If You Can"
  },
  {
   "actorName": "Ben Johnson",
   "movieName": "Radio Flyer"
  },
  {
   "actorName": "Kyle Davis",
   "movieName": "Catch Me If You Can"
  },
  {
   "actorName": "Sam Rockwell",
   "movieName": "The Green Mile"
  },
  {
   "actorName": "Tress MacNeille",
   "movieName": "The Simpsons Movie"
  },
  {
   "actorName": "Jim Broadbent",
   "movieName": "Cloud Atlas"
  },
  {
   "actorName": "John Henry Cox",
   "movieName": "Bridge of Spies"
  },
  {
   "actorName": "John Candy",
   "movieName": "Splash"
  },
  {
   "actorName": "Margo Moorer",
   "movieName": "Forrest Gump"
  },
  {
   "actorName": "John Cygan",
   "movieName": "Toy Story 3"
  },
  {
   "actorName": "Bob Costas",
   "movieName": "Cars"
  },
  {
   "actorName": "Renée Coleman",
   "movieName": "A League of Their Own"
  },
  {
   "actorName": "Mel Gibson",
   "movieName": "Who Killed the Electric Car?"
  },
  {
   "actorName": "David L. Lander",
   "movieName": "A League of Their Own"
  },
  {
   "actorName": "Liv Tyler",
   "movieName": "That Thing You Do!"
  },
  {
   "actorName": "Raevan Lee Hanan",
   "movieName": "Cloud Atlas"
  },
  {
   "actorName": "Kevin Bacon",
   "movieName": "Apollo 13"
  },
  {
   "actorName": "Kurt Naebig",
   "movieName": "Road to Perdition"
  },
  {
   "actorName": "Gary Sinise",
   "movieName": "Apollo 13"
  },
  {
   "actorName": "Gary Sinise",
   "movieName": "The Green Mile"
  },
  {
   "actorName": "Gary Sinise",
   "movieName": "Forrest Gump"
  },
  {
   "actorName": "George Carlin",
   "movieName": "Cars"
  },
  {
   "actorName": "Tom Toner",
   "movieName": "Splash"
  },
  {
   "actorName": "Denzel Washington",
   "movieName": "Philadelphia"
  },
  {
   "actorName": "Vanessa Roth",
   "movieName": "Forrest Gump"
  },
  {
   "actorName": "Margaret Travolta",
   "movieName": "Catch Me If You Can"
  },
  {
   "actorName": "Dale Earnhardt Jr.",
   "movieName": "Cars"
  },
  {
   "actorName": "Agathe Natanson",
   "movieName": "The Da Vinci Code"
  },
  {
   "actorName": "Eddie Deezen",
   "movieName": "The Polar Express"
  },
  {
   "actorName": "Tina Maskell",
   "movieName": "The Da Vinci Code"
  },
  {
   "actorName": "Denis O'Hare",
   "movieName": "Charlie Wilson's War"
  },
  {
   "actorName": "Colette Whitaker",
   "movieName": "Toy Story 3"
  },
  {
   "actorName": "Paul Garcia",
   "movieName": "Saving Private Ryan"
  },
  {
   "actorName": "Anne Ramsay",
   "movieName": "A League of Their Own"
  },
  {
   "actorName": "Pamela Hayden",
   "movieName": "The Simpsons Movie"
  },
  {
   "actorName": "John Mazzello",
   "movieName": "Radio Flyer"
  },
  {
   "actorName": "Dody Goodman",
   "movieName": "Splash"
  },
  {
   "actorName": "Noah Schnapp",
   "movieName": "Bridge of Spies"
  },
  {
   "actorName": "Robin Morrissey",
   "movieName": "Cloud Atlas"
  },
  {
   "actorName": "Daniel Eric Gold",
   "movieName": "Charlie Wilson's War"
  },
  {
   "actorName": "David Pasquesi",
   "movieName": "Angels \u0026 Demons"
  },
  {
   "actorName": "Etienne Chicot",
   "movieName": "The Da Vinci Code"
  },
  {
   "actorName": "Kerry Rossall",
   "movieName": "Road to Perdition"
  },
  {
   "actorName": "Domenick Lombardozzi",
   "movieName": "Bridge of Spies"
  },
  {
   "actorName": "Bob Bowersox",
   "movieName": "Philadelphia"
  },
  {
   "actorName": "Michael Simon Hall",
   "movieName": "Bridge of Spies"
  },
  {
   "actorName": "Peter Miles",
   "movieName": "Saving Private Ryan"
  },
  {
   "actorName": "Michael Burgess",
   "movieName": "Forrest Gump"
  },
  {
   "actorName": "Johnathon Schaech",
   "movieName": "That Thing You Do!"
  },
  {
   "actorName": "Michael Nouri",
   "movieName": "The Terminal"
  },
  {
   "actorName": "Carmen Argenziano",
   "movieName": "Angels \u0026 Demons"
  },
  {
   "actorName": "Lauren Birkell",
   "movieName": "Cast Away"
  },
  {
   "actorName": "Joshua Boyd",
   "movieName": "Catch Me If You Can"
  },
  {
   "actorName": "Sean Baca",
   "movieName": "Radio Flyer"
  },
  {
   "actorName": "Geena Davis",
   "movieName": "A League of Their Own"
  },
  {
   "actorName": "John McConnell",
   "movieName": "The Ladykillers"
  },
  {
   "actorName": "Keith Kupferer",
   "movieName": "Road to Perdition"
  },
  {
   "actorName": "Celine du Tertre",
   "movieName": "Catch Me If You Can"
  },
  {
   "actorName": "Wallace Shawn",
   "movieName": "Toy Story 3"
  },
  {
   "actorName": "Wallace Shawn",
   "movieName": "Toy Story 2"
  },
  {
   "actorName": "Wallace Shawn",
   "movieName": "Toy Story"
  },
  {
   "actorName": "Jan Rabson",
   "movieName": "Toy Story 3"
  },
  {
   "actorName": "John Lasseter",
   "movieName": "Toy Story 2"
  },
  {
   "actorName": "Humpy Wheeler",
   "movieName": "Cars"
  },
  {
   "actorName": "Kristof Konrad",
   "movieName": "Angels \u0026 Demons"
  },
  {
   "actorName": "Kathy Baker",
   "movieName": "Saving Mr. Banks"
  },
  {
   "actorName": "Kelli Simpkins",
   "movieName": "A League of Their Own"
  },
  {
   "actorName": "Ritchie Montgomery",
   "movieName": "Catch Me If You Can"
  },
  {
   "actorName": "Max Mauff",
   "movieName": "Bridge of Spies"
  },
  {
   "actorName": "Victoria Leigh",
   "movieName": "Bridge of Spies"
  },
  {
   "actorName": "Hamilton Clancy",
   "movieName": "Bridge of Spies"
  },
  {
   "actorName": "Ronan Vibert",
   "movieName": "Saving Mr. Banks"
  },
  {
   "actorName": "Mark Holton",
   "movieName": "A League of Their Own"
  },
  {
   "actorName": "Scott Adsit",
   "movieName": "The Terminal"
  },
  {
   "actorName": "Daniel Chapman",
   "movieName": "Philadelphia"
  },
  {
   "actorName": "Rini Bell",
   "movieName": "The Terminal"
  },
  {
   "actorName": "Lowell Ganz",
   "movieName": "Splash"
  },
  {
   "actorName": "Allan Wasserman",
   "movieName": "Big"
  },
  {
   "actorName": "Mark Zak",
   "movieName": "Bridge of Spies"
  },
  {
   "actorName": "Kelly Hutchinson",
   "movieName": "Catch Me If You Can"
  },
  {
   "actorName": "George Anthony Bell",
   "movieName": "The Ladykillers"
  },
  {
   "actorName": "Steve Kehela",
   "movieName": "Angels \u0026 Demons"
  },
  {
   "actorName": "Steve Zahn",
   "movieName": "You've Got Mail"
  },
  {
   "actorName": "Steve Zahn",
   "movieName": "That Thing You Do!"
  },
  {
   "actorName": "Tom Sizemore",
   "movieName": "Saving Private Ryan"
  },
  {
   "actorName": "Mike Simmrin",
   "movieName": "Radio Flyer"
  },
  {
   "actorName": "Kam Heskin",
   "movieName": "Catch Me If You Can"
  },
  {
   "actorName": "Joel Brady",
   "movieName": "Bridge of Spies"
  },
  {
   "actorName": "Ana Maria Quintana",
   "movieName": "Catch Me If You Can"
  },
  {
   "actorName": "Ken Stott",
   "movieName": "Charlie Wilson's War"
  },
  {
   "actorName": "Dan Castellaneta",
   "movieName": "The Simpsons Movie"
  },
  {
   "actorName": "Bill Gratton",
   "movieName": "The Green Mile"
  },
  {
   "actorName": "Pascal Larouche",
   "movieName": "Catch Me If You Can"
  },
  {
   "actorName": "Amy Adams",
   "movieName": "Charlie Wilson's War"
  },
  {
   "actorName": "Amy Adams",
   "movieName": "Catch Me If You Can"
  },
  {
   "actorName": "Mary Steenburgen",
   "movieName": "Philadelphia"
  },
  {
   "actorName": "Amanda Walker",
   "movieName": "Cloud Atlas"
  },
  {
   "actorName": "Eugene Levy",
   "movieName": "Splash"
  },
  {
   "actorName": "Xavier J. Nathan",
   "movieName": "Angels \u0026 Demons"
  },
  {
   "actorName": "Caleb Reynolds",
   "movieName": "Extremely Loud \u0026 Incredibly Close"
  },
  {
   "actorName": "William Shipman",
   "movieName": "Forrest Gump"
  },
  {
   "actorName": "Annie Rose Buckley",
   "movieName": "Saving Mr. Banks"
  },
  {
   "actorName": "Victor Schefé",
   "movieName": "Bridge of Spies"
  },
  {
   "actorName": "Garette Ratliff Henson",
   "movieName": "Radio Flyer"
  },
  {
   "actorName": "Robert Symonds",
   "movieName": "Catch Me If You Can"
  },
  {
   "actorName": "Rachel Singer",
   "movieName": "The Green Mile"
  },
  {
   "actorName": "Shaun Lawton",
   "movieName": "Cloud Atlas"
  },
  {
   "actorName": "David Brisbin",
   "movieName": "Forrest Gump"
  },
  {
   "actorName": "Mark Matheisen",
   "movieName": "Forrest Gump"
  },
  {
   "actorName": "Ben Whishaw",
   "movieName": "Cloud Atlas"
  },
  {
   "actorName": "Philip Rosenthal",
   "movieName": "The Simpsons Movie"
  },
  {
   "actorName": "Sandra Bullock",
   "movieName": "Extremely Loud \u0026 Incredibly Close"
  },
  {
   "actorName": "David Darlow",
   "movieName": "Road to Perdition"
  },
  {
   "actorName": "Megan Cavanagh",
   "movieName": "A League of Their Own"
  },
  {
   "actorName": "Thomas Crawford",
   "movieName": "Catch Me If You Can"
  },
  {
   "actorName": "Alan Alda",
   "movieName": "Bridge of Spies"
  },
  {
   "actorName": "Vincent Généreux",
   "movieName": "Catch Me If You Can"
  },
  {
   "actorName": "Andy Robb",
   "movieName": "The Da Vinci Code"
  },
  {
   "actorName": "Thure Lindhardt",
   "movieName": "Angels \u0026 Demons"
  },
  {
   "actorName": "Michael Schumacher",
   "movieName": "Cars"
  },
  {
   "actorName": "Paul Giamatti",
   "movieName": "Saving Private Ryan"
  },
  {
   "actorName": "Paul Giamatti",
   "movieName": "Saving Mr. Banks"
  },
  {
   "actorName": "Leonardo DiCaprio",
   "movieName": "Catch Me If You Can"
  },
  {
   "actorName": "Anna Katarina",
   "movieName": "Angels \u0026 Demons"
  },
  {
   "actorName": "Hallee Hirsh",
   "movieName": "You've Got Mail"
  },
  {
   "actorName": "Jamie Moss",
   "movieName": "Catch Me If You Can"
  },
  {
   "actorName": "Kathleen Quinlan",
   "movieName": "Apollo 13"
  },
  {
   "actorName": "Richard B. Shull",
   "movieName": "Splash"
  },
  {
   "actorName": "John Voldstad",
   "movieName": "Forrest Gump"
  },
  {
   "actorName": "Jerome Ranft",
   "movieName": "Toy Story 3"
  },
  {
   "actorName": "Neil Finnighan",
   "movieName": "Saving Private Ryan"
  },
  {
   "actorName": "Kirk Ward",
   "movieName": "Forrest Gump"
  },
  {
   "actorName": "Jennifer Echols",
   "movieName": "The Ladykillers"
  },
  {
   "actorName": "Jan Munroe",
   "movieName": "Catch Me If You Can"
  },
  {
   "actorName": "Erick Avari",
   "movieName": "Charlie Wilson's War"
  },
  {
   "actorName": "Maria Canals-Barrera",
   "movieName": "Larry Crowne"
  },
  {
   "actorName": "Daryl Hannah",
   "movieName": "Splash"
  },
  {
   "actorName": "Darrell Waltrip",
   "movieName": "Cars"
  },
  {
   "actorName": "Franklin Amobi",
   "movieName": "Angels \u0026 Demons"
  },
  {
   "actorName": "Ben Bela Böhm",
   "movieName": "Angels \u0026 Demons"
  },
  {
   "actorName": "Brendan Shanahan",
   "movieName": "Forrest Gump"
  },
  {
   "actorName": "Aaron Michael Lacey",
   "movieName": "Forrest Gump"
  },
  {
   "actorName": "Ed Francis Martin",
   "movieName": "Angels \u0026 Demons"
  },
  {
   "actorName": "Julien Normandeau",
   "movieName": "Catch Me If You Can"
  },
  {
   "actorName": "Steve Eastin",
   "movieName": "Catch Me If You Can"
  },
  {
   "actorName": "Bradley Whitford",
   "movieName": "Saving Mr. Banks"
  },
  {
   "actorName": "Bradley Whitford",
   "movieName": "Philadelphia"
  },
  {
   "actorName": "Stephen Bridgewater",
   "movieName": "Forrest Gump"
  },
  {
   "actorName": "Nora Dunfee",
   "movieName": "Forrest Gump"
  },
  {
   "actorName": "Siobhan Fallon",
   "movieName": "Forrest Gump"
  },
  {
   "actorName": "Lorna Guity Pruce",
   "movieName": "Extremely Loud \u0026 Incredibly Close"
  },
  {
   "actorName": "Joseph Mazzello",
   "movieName": "Radio Flyer"
  },
  {
   "actorName": "Barkhad Abdirahman",
   "movieName": "Captain Phillips"
  },
  {
   "actorName": "Ewan McGregor",
   "movieName": "Angels \u0026 Demons"
  },
  {
   "actorName": "Ann Dowd",
   "movieName": "Philadelphia"
  },
  {
   "actorName": "Doug Hutchison",
   "movieName": "The Green Mile"
  },
  {
   "actorName": "Vanness Wu",
   "movieName": "Cars"
  },
  {
   "actorName": "Vin Diesel",
   "movieName": "Saving Private Ryan"
  },
  {
   "actorName": "Bruce Campbell",
   "movieName": "The Ladykillers"
  },
  {
   "actorName": "Brian Libby",
   "movieName": "The Green Mile"
  },
  {
   "actorName": "Zoe Caldwell",
   "movieName": "Extremely Loud \u0026 Incredibly Close"
  },
  {
   "actorName": "Jack Willis",
   "movieName": "Toy Story 3"
  },
  {
   "actorName": "Mikhail Gorevoy",
   "movieName": "Bridge of Spies"
  },
  {
   "actorName": "Mercedes Cornett",
   "movieName": "Catch Me If You Can"
  },
  {
   "actorName": "Rita Wilson",
   "movieName": "Larry Crowne"
  },
  {
   "actorName": "Rita Wilson",
   "movieName": "That Thing You Do!"
  },
  {
   "actorName": "Nicolas Cade",
   "movieName": "Road to Perdition"
  },
  {
   "actorName": "Thomas Horn",
   "movieName": "Extremely Loud \u0026 Incredibly Close"
  },
  {
   "actorName": "Mahat M. Ali",
   "movieName": "Captain Phillips"
  },
  {
   "actorName": "Patrick Thomas O'Brien",
   "movieName": "Catch Me If You Can"
  },
  {
   "actorName": "Rami Malek",
   "movieName": "Larry Crowne"
  },
  {
   "actorName": "George Takei",
   "movieName": "Larry Crowne"
  },
  {
   "actorName": "Steven Griffith",
   "movieName": "Forrest Gump"
  },
  {
   "actorName": "Lisa Talerico",
   "movieName": "Philadelphia"
  },
  {
   "actorName": "Michael Forest",
   "movieName": "Cast Away"
  },
  {
   "actorName": "Gregory Korostishevsky",
   "movieName": "Extremely Loud \u0026 Incredibly Close"
  },
  {
   "actorName": "Chris Ellis",
   "movieName": "Apollo 13"
  },
  {
   "actorName": "Chris Ellis",
   "movieName": "Catch Me If You Can"
  },
  {
   "actorName": "Chris Ellis",
   "movieName": "That Thing You Do!"
  },
  {
   "actorName": "Adam Goldberg",
   "movieName": "Saving Private Ryan"
  },
  {
   "actorName": "Nikolaj Lie Kaas",
   "movieName": "Angels \u0026 Demons"
  },
  {
   "actorName": "Dave Foley",
   "movieName": "Cars"
  },
  {
   "actorName": "Fritz Michel",
   "movieName": "Angels \u0026 Demons"
  },
  {
   "actorName": "Victor Solé",
   "movieName": "Cloud Atlas"
  },
  {
   "actorName": "Michael Schenk",
   "movieName": "Bridge of Spies"
  },
  {
   "actorName": "Michael Conner Humphreys",
   "movieName": "Forrest Gump"
  },
  {
   "actorName": "Marc Cass",
   "movieName": "Saving Private Ryan"
  },
  {
   "actorName": "Mercedes Ruehl",
   "movieName": "Big"
  },
  {
   "actorName": "Dylan Bruno",
   "movieName": "Saving Private Ryan"
  },
  {
   "actorName": "Brian Hutchison",
   "movieName": "Bridge of Spies"
  },
  {
   "actorName": "Nia Vardalos",
   "movieName": "Larry Crowne"
  },
  {
   "actorName": "Michael Pemberton",
   "movieName": "Bridge of Spies"
  },
  {
   "actorName": "Kitty Carlisle",
   "movieName": "Catch Me If You Can"
  },
  {
   "actorName": "Michael Sassone",
   "movieName": "Road to Perdition"
  },
  {
   "actorName": "Ted Danson",
   "movieName": "Saving Private Ryan"
  },
  {
   "actorName": "Peter Dobson",
   "movieName": "Forrest Gump"
  },
  {
   "actorName": "Greg Brown",
   "movieName": "Forrest Gump"
  },
  {
   "actorName": "Gino Conforti",
   "movieName": "Angels \u0026 Demons"
  },
  {
   "actorName": "Isabel Rose",
   "movieName": "Forrest Gump"
  },
  {
   "actorName": "Lydia Blanco Garza",
   "movieName": "The Terminal"
  },
  {
   "actorName": "Lindsey Collins",
   "movieName": "Cars"
  },
  {
   "actorName": "Gary Sefton",
   "movieName": "Saving Private Ryan"
  },
  {
   "actorName": "Elissa Knight",
   "movieName": "Cars"
  },
  {
   "actorName": "Penn Jillette",
   "movieName": "Toy Story"
  },
  {
   "actorName": "Hallie D'Amore",
   "movieName": "Forrest Gump"
  },
  {
   "actorName": "Matt Wallace",
   "movieName": "Forrest Gump"
  },
  {
   "actorName": "Adam LeFevre",
   "movieName": "Philadelphia"
  },
  {
   "actorName": "Tzi Ma",
   "movieName": "The Ladykillers"
  },
  {
   "actorName": "Fred Lerner",
   "movieName": "Splash"
  },
  {
   "actorName": "Stephen Root",
   "movieName": "The Ladykillers"
  },
  {
   "actorName": "Markus Napier",
   "movieName": "Saving Private Ryan"
  },
  {
   "actorName": "Emily Ann Lloyd",
   "movieName": "Apollo 13"
  },
  {
   "actorName": "Colin Hanks",
   "movieName": "That Thing You Do!"
  },
  {
   "actorName": "Daniel Bieber",
   "movieName": "Radio Flyer"
  },
  {
   "actorName": "Nancy Cartwright",
   "movieName": "The Simpsons Movie"
  },
  {
   "actorName": "Elizabeth Perkins",
   "movieName": "Big"
  },
  {
   "actorName": "Taraji P. Henson",
   "movieName": "Larry Crowne"
  },
  {
   "actorName": "Frank John Hughes",
   "movieName": "Catch Me If You Can"
  },
  {
   "actorName": "Jonas Rivera",
   "movieName": "Cars"
  },
  {
   "actorName": "Leslie Zemeckis",
   "movieName": "The Polar Express"
  },
  {
   "actorName": "Mark Sorensen Jr.",
   "movieName": "Philadelphia"
  },
  {
   "actorName": "Leonid Citer",
   "movieName": "Cast Away"
  },
  {
   "actorName": "Michael Jace",
   "movieName": "Forrest Gump"
  },
  {
   "actorName": "Fuschia Sumner",
   "movieName": "Saving Mr. Banks"
  },
  {
   "actorName": "John Ratzenberger",
   "movieName": "Toy Story 3"
  },
  {
   "actorName": "John Ratzenberger",
   "movieName": "Toy Story 2"
  },
  {
   "actorName": "John Ratzenberger",
   "movieName": "Cars"
  },
  {
   "actorName": "John Ratzenberger",
   "movieName": "Toy Story"
  },
  {
   "actorName": "Timothy Dalton",
   "movieName": "Toy Story 3"
  },
  {
   "actorName": "Paul Dooley",
   "movieName": "Cars"
  },
  {
   "actorName": "Stephanie Kurtzuba",
   "movieName": "Extremely Loud \u0026 Incredibly Close"
  },
  {
   "actorName": "Jamie Anderson",
   "movieName": "Catch Me If You Can"
  },
  {
   "actorName": "Martin Sheen",
   "movieName": "Catch Me If You Can"
  },
  {
   "actorName": "Martin Sheen",
   "movieName": "Who Killed the Electric Car?"
  },
  {
   "actorName": "Katie Sagona",
   "movieName": "You've Got Mail"
  },
  {
   "actorName": "Elijah Wood",
   "movieName": "Radio Flyer"
  },
  {
   "actorName": "Peter McRobbie",
   "movieName": "Bridge of Spies"
  },
  {
   "actorName": "Om Puri",
   "movieName": "Charlie Wilson's War"
  },
  {
   "actorName": "Diego Luna",
   "movieName": "The Terminal"
  },
  {
   "actorName": "Eugene Fleming",
   "movieName": "Catch Me If You Can"
  },
  {
   "actorName": "Robert Malone",
   "movieName": "The Green Mile"
  },
  {
   "actorName": "Mickie McGowan",
   "movieName": "Toy Story 3"
  },
  {
   "actorName": "Mickie McGowan",
   "movieName": "Toy Story 2"
  },
  {
   "actorName": "Joey Slotnick",
   "movieName": "A League of Their Own"
  },
  {
   "actorName": "Chris Isaak",
   "movieName": "That Thing You Do!"
  },
  {
   "actorName": "Ellen Pompeo",
   "movieName": "Catch Me If You Can"
  },
  {
   "actorName": "Lauren Roselli",
   "movieName": "Philadelphia"
  },
  {
   "actorName": "Michael McFall",
   "movieName": "Forrest Gump"
  },
  {
   "actorName": "Mark Rylance",
   "movieName": "Bridge of Spies"
  },
  {
   "actorName": "Mike Houston",
   "movieName": "Bridge of Spies"
  },
  {
   "actorName": "Tony Shalhoub",
   "movieName": "Cars"
  },
  {
   "actorName": "Martin Hub",
   "movieName": "Saving Private Ryan"
  },
  {
   "actorName": "Scotty Leavenworth",
   "movieName": "The Green Mile"
  },
  {
   "actorName": "Brian Howe",
   "movieName": "Catch Me If You Can"
  },
  {
   "actorName": "Daniel Craig",
   "movieName": "Road to Perdition"
  },
  {
   "actorName": "Jonathan Brent",
   "movieName": "Catch Me If You Can"
  },
  {
   "actorName": "Jean Stapleton",
   "movieName": "You've Got Mail"
  },
  {
   "actorName": "Daniel J. Gillooly",
   "movieName": "Forrest Gump"
  },
  {
   "actorName": "Gugu Mbatha-Raw",
   "movieName": "Larry Crowne"
  },
  {
   "actorName": "Don S. Davis",
   "movieName": "A League of Their Own"
  },
  {
   "actorName": "Jess Harnell",
   "movieName": "Toy Story 3"
  },
  {
   "actorName": "David Andrews",
   "movieName": "Apollo 13"
  },
  {
   "actorName": "Patricia Squire",
   "movieName": "Bridge of Spies"
  },
  {
   "actorName": "Ian McKellen",
   "movieName": "The Da Vinci Code"
  },
  {
   "actorName": "Stellan Skarsgård",
   "movieName": "Angels \u0026 Demons"
  },
  {
   "actorName": "Tracy Reiner",
   "movieName": "Apollo 13"
  },
  {
   "actorName": "Tracy Reiner",
   "movieName": "A League of Their Own"
  },
  {
   "actorName": "Victor Alfieri",
   "movieName": "Angels \u0026 Demons"
  },
  {
   "actorName": "Jennifer Jason Leigh",
   "movieName": "Road to Perdition"
  },
  {
   "actorName": "Walter K. Jordan",
   "movieName": "The Ladykillers"
  },
  {
   "actorName": "Bob Peterson",
   "movieName": "Toy Story 3"
  },
  {
   "actorName": "Rance Howard",
   "movieName": "Angels \u0026 Demons"
  },
  {
   "actorName": "Owen Wilson",
   "movieName": "Cars"
  },
  {
   "actorName": "Rob Maxey",
   "movieName": "Road to Perdition"
  },
  {
   "actorName": "Antoine Drolet-Dumoulin",
   "movieName": "Catch Me If You Can"
  },
  {
   "actorName": "Jean Speegle Howard",
   "movieName": "Apollo 13"
  },
  {
   "actorName": "Corey Johnson",
   "movieName": "Captain Phillips"
  },
  {
   "actorName": "Jim Varney",
   "movieName": "Toy Story 2"
  },
  {
   "actorName": "Jim Varney",
   "movieName": "Toy Story"
  },
  {
   "actorName": "Steven Boyer",
   "movieName": "Bridge of Spies"
  },
  {
   "actorName": "Joe Spano",
   "movieName": "Apollo 13"
  },
  {
   "actorName": "Peter von Berg",
   "movieName": "Cast Away"
  },
  {
   "actorName": "Stan Bly",
   "movieName": "Catch Me If You Can"
  },
  {
   "actorName": "Barkhad Abdi",
   "movieName": "Captain Phillips"
  },
  {
   "actorName": "Michael Clarke Duncan",
   "movieName": "The Green Mile"
  },
  {
   "actorName": "Hugh Grant",
   "movieName": "Cloud Atlas"
  },
  {
   "actorName": "Jürgen Prochnow",
   "movieName": "The Da Vinci Code"
  },
  {
   "actorName": "Laraine Newman",
   "movieName": "Toy Story 3"
  },
  {
   "actorName": "Jasmine Jessica Anthony",
   "movieName": "Catch Me If You Can"
  },
  {
   "actorName": "Garry Marshall",
   "movieName": "A League of Their Own"
  },
  {
   "actorName": "Florent Legault",
   "movieName": "Catch Me If You Can"
  },
  {
   "actorName": "Cosimo Fusco",
   "movieName": "Angels \u0026 Demons"
  },
  {
   "actorName": "Tom Everett Scott",
   "movieName": "That Thing You Do!"
  },
  {
   "actorName": "Lisa Summerour",
   "movieName": "Philadelphia"
  },
  {
   "actorName": "Léon Dussault-Gagné",
   "movieName": "Catch Me If You Can"
  },
  {
   "actorName": "Ashley Cohen",
   "movieName": "Catch Me If You Can"
  },
  {
   "actorName": "Marlena Smalls",
   "movieName": "Forrest Gump"
  },
  {
   "actorName": "Corey Burton",
   "movieName": "Toy Story 2"
  },
  {
   "actorName": "Mack Miles",
   "movieName": "The Green Mile"
  },
  {
   "actorName": "Mike Baldridge",
   "movieName": "Catch Me If You Can"
  },
  {
   "actorName": "Michael Power",
   "movieName": "Bridge of Spies"
  },
  {
   "actorName": "John Heard",
   "movieName": "Radio Flyer"
  },
  {
   "actorName": "John Heard",
   "movieName": "Big"
  },
  {
   "actorName": "Viola Davis",
   "movieName": "Extremely Loud \u0026 Incredibly Close"
  },
  {
   "actorName": "Marko Caka",
   "movieName": "Bridge of Spies"
  },
  {
   "actorName": "Scott Shepherd",
   "movieName": "Bridge of Spies"
  },
  {
   "actorName": "Valerie Colgan",
   "movieName": "Saving Private Ryan"
  },
  {
   "actorName": "Ursula Brooks",
   "movieName": "Angels \u0026 Demons"
  },
  {
   "actorName": "Ed Harris",
   "movieName": "Apollo 13"
  },
  {
   "actorName": "Jennifer Garner",
   "movieName": "Catch Me If You Can"
  },
  {
   "actorName": "Tony Fitzpatrick",
   "movieName": "Philadelphia"
  },
  {
   "actorName": "Cyia Batten",
   "movieName": "Charlie Wilson's War"
  },
  {
   "actorName": "Bryan Hanna",
   "movieName": "Forrest Gump"
  },
  {
   "actorName": "Bitty Schram",
   "movieName": "A League of Their Own"
  },
  {
   "actorName": "Zhu Zhu",
   "movieName": "Cloud Atlas"
  },
  {
   "actorName": "James Morrison",
   "movieName": "Catch Me If You Can"
  },
  {
   "actorName": "Nathalie Baye",
   "movieName": "Catch Me If You Can"
  },
  {
   "actorName": "Paul Todd",
   "movieName": "Catch Me If You Can"
  },
  {
   "actorName": "Tak Fujimoto",
   "movieName": "Philadelphia"
  },
  {
   "actorName": "Ashlie Atkinson",
   "movieName": "Bridge of Spies"
  },
  {
   "actorName": "Billy Magnussen",
   "movieName": "Bridge of Spies"
  },
  {
   "actorName": "Elden Henson",
   "movieName": "Radio Flyer"
  },
  {
   "actorName": "Rai Tasco",
   "movieName": "The Green Mile"
  },
  {
   "actorName": "Edward James Hyland",
   "movieName": "Bridge of Spies"
  },
  {
   "actorName": "Michael Jeter",
   "movieName": "The Polar Express"
  },
  {
   "actorName": "Michael Jeter",
   "movieName": "The Green Mile"
  },
  {
   "actorName": "Harry S. Murphy",
   "movieName": "Charlie Wilson's War"
  },
  {
   "actorName": "Mary Ellen Trainor",
   "movieName": "Forrest Gump"
  },
  {
   "actorName": "Rashmi",
   "movieName": "Angels \u0026 Demons"
  },
  {
   "actorName": "Freddie Simpson",
   "movieName": "A League of Their Own"
  },
  {
   "actorName": "Thomas Ian Nicholas",
   "movieName": "Radio Flyer"
  },
  {
   "actorName": "Marlon Wayans",
   "movieName": "The Ladykillers"
  },
  {
   "actorName": "Jeremy Davies",
   "movieName": "Saving Private Ryan"
  },
  {
   "actorName": "Kenneth Utt",
   "movieName": "Philadelphia"
  },
  {
   "actorName": "John Rue",
   "movieName": "Bridge of Spies"
  },
  {
   "actorName": "John Bedford Lloyd",
   "movieName": "Philadelphia"
  },
  {
   "actorName": "Gary Imhoff",
   "movieName": "The Green Mile"
  },
  {
   "actorName": "Robert Peters",
   "movieName": "Catch Me If You Can"
  },
  {
   "actorName": "Valeriy Nikolaev",
   "movieName": "The Terminal"
  },
  {
   "actorName": "Neezer Tarleton",
   "movieName": "A League of Their Own"
  },
  {
   "actorName": "Rosie O'Donnell",
   "movieName": "A League of Their Own"
  },
  {
   "actorName": "Byron Minns",
   "movieName": "Forrest Gump"
  },
  {
   "actorName": "Joe Garagiola, Sr.",
   "movieName": "Catch Me If You Can"
  },
  {
   "actorName": "Duane Sharp",
   "movieName": "Road to Perdition"
  },
  {
   "actorName": "Maria Cristina Heller",
   "movieName": "Angels \u0026 Demons"
  },
  {
   "actorName": "Robert Torti",
   "movieName": "That Thing You Do!"
  },
  {
   "actorName": "Mike Dirnt",
   "movieName": "The Simpsons Movie"
  },
  {
   "actorName": "Robin Knight",
   "movieName": "A League of Their Own"
  },
  {
   "actorName": "Sylvestra Le Touzel",
   "movieName": "Cloud Atlas"
  },
  {
   "actorName": "Whoopi Goldberg",
   "movieName": "Toy Story 3"
  },
  {
   "actorName": "Mark Wheeler",
   "movieName": "Apollo 13"
  },
  {
   "actorName": "Bill Paxton",
   "movieName": "Apollo 13"
  },
  {
   "actorName": "Parker Posey",
   "movieName": "You've Got Mail"
  },
  {
   "actorName": "Michael Keaton",
   "movieName": "Toy Story 3"
  },
  {
   "actorName": "Michael Keaton",
   "movieName": "Cars"
  },
  {
   "actorName": "Douglas Keever",
   "movieName": "Cars"
  },
  {
   "actorName": "Jude Ciccolella",
   "movieName": "The Terminal"
  },
  {
   "actorName": "Kevin Mangan",
   "movieName": "Forrest Gump"
  },
  {
   "actorName": "Ron Komora",
   "movieName": "Bridge of Spies"
  },
  {
   "actorName": "Van Epperson",
   "movieName": "The Green Mile"
  },
  {
   "actorName": "Carlos Alazraqui",
   "movieName": "Toy Story 3"
  },
  {
   "actorName": "Marie-Françoise Audollent",
   "movieName": "The Da Vinci Code"
  },
  {
   "actorName": "Jeffrey Boehm",
   "movieName": "Angels \u0026 Demons"
  },
  {
   "actorName": "Erika Katz",
   "movieName": "Big"
  }
 ]
}
